xsession_manager/__init__.py
xsession_manager/arguments_handler.py
xsession_manager/arguments_parser.py
xsession_manager/main.py
xsession_manager/session_filter.py
xsession_manager/version.py
xsession_manager/xsession_manager.py
xsession_manager/gui/__init__.py
xsession_manager/gui/askyesno_dialog.py
xsession_manager/settings/__init__.py
xsession_manager/settings/constants.py
xsession_manager/settings/xsession_config.py
xsession_manager/tests/__init__.py
xsession_manager/tests/run_main.py
xsession_manager/tests/snapd_workaround_test.py
xsession_manager/tests/wmctl_wapper_test.py
xsession_manager/tests/xsession_manager_test.py
xsession_manager/utils/__init__.py
xsession_manager/utils/base.py
xsession_manager/utils/exceptions.py
xsession_manager/utils/gio_utils.py
xsession_manager/utils/gsettings_wrapper.py
xsession_manager/utils/number_utils.py
xsession_manager/utils/retry.py
xsession_manager/utils/snapd_workaround.py
xsession_manager/utils/string_utils.py
xsession_manager/utils/subprocess_utils.py
xsession_manager/utils/suppress_output.py
xsession_manager/utils/wmctl_wrapper.py
xsession_manager/utils/wnck_utils.py
xsession_manager-1.0.8.dist-info/LICENSE
xsession_manager-1.0.8.dist-info/METADATA
xsession_manager-1.0.8.dist-info/WHEEL
xsession_manager-1.0.8.dist-info/entry_points.txt
xsession_manager-1.0.8.dist-info/top_level.txt
xsession_manager-1.0.8.dist-info/RECORD
