Metadata-Version: 2.1
Name: xsession-manager
Version: 1.0.8
Summary: A command line to save and restore sessions for X11 desktops like Gnome, with many other features
Home-page: https://github.com/nlpsuge/xsession-manager
Author: nlpsuge
Project-URL: Bug Reports, https://github.com/nlpsuge/xsession-manager/issues
Project-URL: Source, https://github.com/nlpsuge/xsession-manager
Keywords: manager,X.org,session,save and restore
Classifier: Development Status :: 4 - Beta
Classifier: Intended Audience :: End Users/Desktop
Classifier: License :: OSI Approved :: GNU Lesser General Public License v3 or later (LGPLv3+)
Classifier: Programming Language :: Python :: 3.6
Classifier: Programming Language :: Python :: 3.7
Classifier: Programming Language :: Python :: 3.8
Classifier: Programming Language :: Python :: 3.9
Classifier: Programming Language :: Python :: 3.10
Classifier: Topic :: Desktop Environment
Classifier: Topic :: System :: Recovery Tools
Classifier: Topic :: Utilities
Requires-Python: >=3
License-File: LICENSE
Requires-Dist: psutil (>=5.7.2)
Requires-Dist: pycurl (>=7.43.0.5)
